{"filename":"db.json","collections":[{"name":"clientes","data":[{"nome":"Suellen Nascimento","tel":"99999999999","bairro":"heehuhe","servico":"ehehehuehe","produto":"euhehehh","obs":"heuheuheuhe","meta":{"revision":0,"created":1525689288920,"version":0},"$loki":1},{"nome":"Eduardo Lohann","tel":"444444","bairro":"44444","servico":"444","produto":"444444","obs":"4444444","meta":{"revision":1,"created":1525700218125,"version":0,"updated":1525700515208},"$loki":2},{"nome":"Larissa Nascimento","tel":"3232232","bairro":"323","servico":"23232","produto":"32","obs":"32","meta":{"revision":0,"created":1525700545600,"version":0},"$loki":3}],"idIndex":[1,2,3],"binaryIndices":{},"constraints":null,"uniqueNames":[],"transforms":{},"objType":"clientes","dirty":false,"cachedIndex":null,"cachedBinaryIndex":null,"cachedData":null,"adaptiveBinaryIndices":true,"transactional":false,"cloneObjects":false,"cloneMethod":"parse-stringify","asyncListeners":false,"disableMeta":false,"disableChangesApi":true,"disableDeltaChangesApi":true,"autoupdate":false,"serializableIndices":true,"ttl":null,"maxId":3,"DynamicViews":[],"events":{"insert":[null],"update":[null],"pre-insert":[],"pre-update":[],"close":[],"flushbuffer":[],"error":[],"delete":[null],"warning":[null]},"changes":[]},{"name":"produtos","data":[{"nome":"Bolo","preco":"192,00","qtd":"1","tipo":"Doce","pobs":"","meta":{"revision":0,"created":1525704531985,"version":0},"$loki":1},{"nome":"Salgados","preco":"19,90","qtd":"80","tipo":"Salgado","desc":"detteedetedtedtededtedetedtededetedte","meta":{"revision":3,"created":1525704646207,"version":0,"updated":1525704744300},"$loki":2}],"idIndex":[1,2],"binaryIndices":{},"constraints":null,"uniqueNames":[],"transforms":{},"objType":"produtos","dirty":false,"cachedIndex":null,"cachedBinaryIndex":null,"cachedData":null,"adaptiveBinaryIndices":true,"transactional":false,"cloneObjects":false,"cloneMethod":"parse-stringify","asyncListeners":false,"disableMeta":false,"disableChangesApi":true,"disableDeltaChangesApi":true,"autoupdate":false,"serializableIndices":true,"ttl":null,"maxId":2,"DynamicViews":[],"events":{"insert":[null],"update":[null],"pre-insert":[],"pre-update":[],"close":[],"flushbuffer":[],"error":[],"delete":[null],"warning":[null]},"changes":[]}],"databaseVersion":1.5,"engineVersion":1.5,"autosave":false,"autosaveInterval":5000,"autosaveHandle":null,"throttledSaves":true,"options":{"serializationMethod":"normal","destructureDelimiter":"$<\n"},"persistenceMethod":"fs","persistenceAdapter":null,"verbose":false,"events":{"init":[null],"loaded":[],"flushChanges":[],"close":[],"changes":[],"warning":[]},"ENV":"NODEJS"}